[
  {
    "data": [
      {
        "x": "Concordo",
        "y": 73
      },
      {
        "x": "Discordo",
        "y": 71
      },
      {
        "x": "Neutro",
        "y": 61
      },
      {
        "x": "Concordo totalmente",
        "y": 15
      },
      {
        "x": "Discordo Totalmente",
        "y": 11
      },
      {
        "x": "Nao sabe",
        "y": 2
      }
    ],
    "title": "Me sinto preparada(o) para educar crianças com deficiências, TEA ou altas habilidades"
  },
  {
    "data": [
      {
        "x": "Não",
        "y": 143
      },
      {
        "x": "Sim",
        "y": 90
      }
    ],
    "title": "Há crianças com diversidades funcionais, transtornos globais do desenvolvimento, altas habilidades ou superdotação nesta turma?"
  },
  {
    "title": "Há crianças com deficiências X Profissionais na unidade dedicados somente ao trabalho com crianças comdeficiência?",
    "data": [
      {
        "x": "Crianças com deficiências",
        "y": 1553
      },
      {
        "x": "Profissionais na unidade dedicados",
        "y": 312
      }
    ]
  }
]
